admin/__init__.py
admin/admin_app.py
admin/article.py
admin/category.py
admin/user.py
member/__init__.py
member/article.py
member/comment.py
member/member_app.py
member/user.py
Flask_CMS_XP-0.1.0.dist-info/METADATA
Flask_CMS_XP-0.1.0.dist-info/WHEEL
Flask_CMS_XP-0.1.0.dist-info/top_level.txt
Flask_CMS_XP-0.1.0.dist-info/RECORD
